wageubn/__init__.py
wageubn/__version__.py
wageubn/config.py
wageubn/utils.py
wageubn/function/__init__.py
wageubn/function/_utils.py
wageubn/function/activation.py
wageubn/function/adder.py
wageubn/function/batchnorm.py
wageubn/function/conv.py
wageubn/function/linear.py
wageubn/function/number.py
wageubn/function/extra/__init__.py
wageubn/function/extra/adder.py
wageubn-1.2.0.dist-info/LICENSE
wageubn-1.2.0.dist-info/METADATA
wageubn-1.2.0.dist-info/WHEEL
wageubn-1.2.0.dist-info/top_level.txt
wageubn-1.2.0.dist-info/RECORD
