Metadata-Version: 2.1
Name: wageubn
Version: 1.2.0
Summary: torch implement of WAGEUBN
Home-page: https://github.com/PannenetsF/WAGEUBN
Author: Pannenets F
Author-email: pannenets.f@foxmail.com
License: BSD-3-Clause License
Keywords: quantization NN torch
Platform: UNKNOWN
Classifier: Development Status :: 4 - Beta
Classifier: Environment :: GPU
Classifier: Intended Audience :: Science/Research
Classifier: License :: OSI Approved :: BSD License
Classifier: Operating System :: OS Independent
Classifier: Programming Language :: Python
Requires-Python: >=3.7.*
Requires-Dist: torch
